medialogue/__init__.py
medialogue/admin.py
medialogue/apps.py
medialogue/context_processors.py
medialogue/forms.py
medialogue/models.py
medialogue/signals.py
medialogue/tasks.py
medialogue/urls.py
medialogue/utils.py
medialogue/views.py
medialogue/api/__init__.py
medialogue/api/urls.py
medialogue/api/views.py
medialogue/migrations/0001_initial.py
medialogue/migrations/0002_auto_20230315_1256.py
medialogue/migrations/0003_alter_media_title.py
medialogue/migrations/__init__.py
medialogue/migrations/__pycache__/0001_initial.cpython-37.pyc
medialogue/migrations/__pycache__/0002_auto_20230315_1256.cpython-37.pyc
medialogue/migrations/__pycache__/0003_alter_media_title.cpython-37.pyc
medialogue/migrations/__pycache__/0003_auto_20230403_1230.cpython-37.pyc
medialogue/migrations/__pycache__/__init__.cpython-37.pyc
medialogue/static/medialogue/css/style.css
medialogue/static/medialogue/js/album_edit.js
medialogue/static/medialogue/js/medialogue-filepond.js
medialogue/templates/base.html
medialogue/templates/medialogue/album_detail.html
medialogue/templates/medialogue/album_edit.html
medialogue/templates/medialogue/album_list.html
medialogue/templates/medialogue/new-album.html
medialogue/templates/medialogue/photo_detail.html
medialogue/templates/medialogue/photo_list.html
medialogue/templates/medialogue/video_detail.html
medialogue/templates/medialogue/video_list.html
medialogue/templates/medialogue/tags/next_in_album.html
medialogue/templates/medialogue/tags/prev_in_album.html
medialogue/templatetags/__init__.py
medialogue/templatetags/medialogue_tags.py
medialogue/templatetags/__pycache__/__init__.cpython-37.pyc
medialogue/templatetags/__pycache__/medialogue_tags.cpython-37.pyc
medialogue/tests/__init__.py
medialogue/tests/factories.py
medialogue/tests/helpers.py
medialogue/tests/test_album.py
medialogue/tests/test_api.py
medialogue/tests/test_medialogue_forms.py
medialogue/tests/test_medialogue_models.py
medialogue/tests/test_photo.py
medialogue/tests/test_sites.py
django_medialogue-2.0.17.dist-info/METADATA
django_medialogue-2.0.17.dist-info/WHEEL
django_medialogue-2.0.17.dist-info/top_level.txt
django_medialogue-2.0.17.dist-info/RECORD
