Metadata-Version: 2.1
Name: django-medialogue
Version: 2.0.17
Summary: An Fork of django-medialogue with video support
Home-page: https://github.com/derek-adair/medialogue
Author: Derek Adair
Author-email: d@derekadair.com
License: UNKNOWN
Platform: UNKNOWN
Classifier: Development Status :: 5 - Production/Stable
Classifier: Environment :: Web Environment
Classifier: Framework :: Django
Classifier: Intended Audience :: Developers
Classifier: License :: OSI Approved :: BSD License
Classifier: Operating System :: OS Independent
Classifier: Programming Language :: Python
Classifier: Programming Language :: Python :: 3
Classifier: Programming Language :: Python :: 3.4
Classifier: Programming Language :: Python :: 3.5
Classifier: Programming Language :: Python :: 3.6
Classifier: Topic :: Utilities
Requires-Dist: django-drf-filepond
Requires-Dist: django-ordered-model (==3.7.2)
Requires-Dist: django-rq
Requires-Dist: django-video-encoding (<2.0,>=1.0)
Requires-Dist: django (<4.0,>=3.0)
Requires-Dist: djangorestframework
Requires-Dist: easy-thumbnails[svg]
Requires-Dist: psycopg2
Requires-Dist: pytest-django
Requires-Dist: python-magic
Requires-Dist: redis
